tw_stocks/__init__.py
tw_stocks/client.py
tw_stocks-0.1.1.dist-info/LICENSE
tw_stocks-0.1.1.dist-info/METADATA
tw_stocks-0.1.1.dist-info/WHEEL
tw_stocks-0.1.1.dist-info/top_level.txt
tw_stocks-0.1.1.dist-info/RECORD
